{
  "crawled_slug": "menlo-park-ca-pd",
  "crawled_name": "Menlo Park CA PD",
  "archived_date": "2026-04-03",
  "whats_detected": "License Plates, Vehicles",
  "whats_not_detected": "Facial recognition, People, Gender, Race",
  "acceptable_use_policy": "Data is used for law enforcement purposes only. Data is owned by Menlo Park CA PD and is never sold to 3rd parties.",
  "prohibited_uses": "Immigration enforcement, traffic enforcement, harassment or intimidation, usage based solely on a protected class (i.e. race, sex, religion), Personal use.",
  "access_policy": "All system access requires a valid reason and is stored indefinitely.",
  "hotlist_policy": "Hotlist hits are required to be human verified prior to action.",
  "sharing_with_partners": "",
  "sharing_restrictions": "",
  "data_retention_days": 30,
  "camera_count": 32,
  "hotlists_alerted_on": "California SVS, NCMEC Amber Alert",
  "vehicles_detected_30d": 795487,
  "hotlist_hits_30d": 17407,
  "searches_30d": 142,
  "sharing_outbound": [
    "Alameda County CA SO",
    "Albany CA PD",
    "Alhambra CA PD",
    "Amador County CA Sheriff's Office",
    "Anaheim CA PD",
    "Anderson CA PD",
    "Angels Camp CA PD",
    "Antioch CA PD",
    "Arcadia CA PD",
    "Atherton CA PD",
    "Atwater CA PD",
    "Auburn CA PD",
    "Azusa CA PD",
    "Bakersfield CA PD",
    "Baldwin Park CA PD",
    "Beaumont CA PD",
    "Belmont CA PD",
    "Belvedere CA PD",
    "Benicia CA PD",
    "Beverly Hills CA PD",
    "Bishop CA PD",
    "Brawley CA PD",
    "Brentwood CA PD",
    "Brisbane CA PD",
    "Buena Park CA PD",
    "Burbank CA PD",
    "Burlingame CA PD",
    "Butte County CA SO",
    "Cal Fire",
    "Cal State Fullerton (CA)",
    "California Department of Corrections",
    "California Highway Patrol",
    "California State Parks",
    "Calistoga CA PD",
    "Campbell CA PD",
    "Capitola CA PD",
    "Carmel CA PD",
    "Central Marin CA PD",
    "Chino CA PD",
    "Chula Vista CA PD",
    "Citrus Heights CA PD",
    "City of Lemoore CA",
    "City of Riverside CA PD",
    "Clayton CA PD",
    "Cloverdale CA PD",
    "Colma CA PD",
    "Colton CA PD",
    "Concord CA PD",
    "Contra Costa County CA SO",
    "Corona CA PD",
    "Coronado CA PD",
    "Costa Mesa CA PD",
    "Covina CA PD",
    "Culver City CA PD",
    "Cypress CA PD",
    "Daly City CA PD",
    "Danville CA PD",
    "Delano CA PD",
    "Desert Hot Springs CA PD",
    "Dinuba CA PD",
    "Dixon CA PD",
    "Downey PD CA",
    "Dublin CA PD (ACSO)",
    "East Bay Parks CA PD",
    "East Palo Alto CA PD",
    "El Cajon CA PD",
    "El Centro CA PD",
    "El Cerrito CA PD",
    "El Monte CA PD",
    "El Segundo CA PD",
    "Elk Grove CA PD",
    "Emeryville CA PD",
    "Escalon CA PD",
    "Escondido CA PD",
    "Fairfield CA PD",
    "Folsom CA PD",
    "Fontana CA PD",
    "Foothill-DeAnza CA PD",
    "Fort Bragg CA PD",
    "Foster City CA PD",
    "Fountain Valley CA PD",
    "Fowler CA PD",
    "Fremont CA PD",
    "Fresno CA PD",
    "Fullerton CA PD",
    "Galt CA PD",
    "Garden Grove CA PD",
    "Gilroy CA PD",
    "Glendora (CA) PD",
    "Grass Valley CA PD",
    "Grover Beach CA PD",
    "Gustine PD CA",
    "Hanford CA PD",
    "Hayward CA PD",
    "Hemet CA PD",
    "Hercules CA PD",
    "Hillsborough CA PD",
    "Hollister CA PD",
    "Imperial City CA PD",
    "Indio CA PD",
    "Irvine CA PD",
    "Irwindale CA PD",
    "Kern County CA SO",
    "Kings County CA DAs Office",
    "Kings County Sheriff's Office CA",
    "La Habra CA PD",
    "La Verne CA PD",
    "Laguna Beach CA PD",
    "Lake County CA SO",
    "Lakeport CA PD",
    "Lincoln CA PD",
    "Livermore CA PD",
    "Livingston CA PD",
    "Lodi CA PD",
    "Lompoc CA PD",
    "Los Alamitos PD CA",
    "Los Altos CA PD",
    "Los Angeles CA PD",
    "Los Angeles County CA SD",
    "Los Angeles Port Police CA",
    "Madera County SO CA",
    "Manteca CA PD",
    "Marin County CA DA",
    "Marin County CA SO",
    "Marina CA PD",
    "Mendocino County SO-CA",
    "Mendota CA PD",
    "Menifee CA PD",
    "Merced County CA SO",
    "Mill Valley CA PD",
    "Milpitas CA PD",
    "Modoc County CA SO",
    "Montclair CA PD",
    "Monterey CA PD",
    "Monterey County CA SO",
    "Monterey Park CA PD",
    "Moraga CA PD",
    "Morgan Hill CA PD",
    "Murrieta CA PD",
    "Napa CA PD",
    "Napa County CA SO",
    "National City CA PD",
    "NCRIC",
    "Nevada City CA PD",
    "Nevada County CA SO",
    "Newark CA PD",
    "Newport Beach PD CA",
    "Novato CA PD",
    "Oakland CA PD",
    "Oakley CA PD",
    "Oceanside CA PD",
    "Ontario CA PD",
    "Orange CA PD",
    "Orange County (CA) DA Office",
    "Orange County SO CA",
    "Oxnard CA PD",
    "Pacific Grove CA PD",
    "Pacifica CA PD",
    "Palo Alto CA PD",
    "Pasadena CA PD",
    "Petaluma CA PD",
    "Placentia CA PD",
    "Placer County CA DA Office",
    "Placer County CA SO",
    "Pleasant Hill CA PD",
    "Pleasanton CA PD",
    "Port of Stockton CA PD",
    "Porterville CA PD",
    "Redding PD - CA",
    "Redondo Beach CA PD",
    "Redwood City CA PD",
    "Rialto PD CA",
    "Ridgecrest CA PD",
    "Rio Vista CA PD",
    "RIV CO ARSON TF CA PD",
    "Riverside County CA SO",
    "Sacramento CA PD",
    "Salinas CA PD",
    "San Bernardino CA PD",
    "San Bernardino County CA SO",
    "San Bruno CA PD",
    "San Diego CA PD",
    "San Diego County CA SD",
    "San Diego Harbor CA PD",
    "San Fernando CA PD",
    "San Francisco CA PD",
    "San Francisco District Attorney CA",
    "San Gabriel CA PD",
    "San Joaquin County CA SO",
    "San Joaquin Delta College PD (CA)",
    "San Jose CA PD",
    "San Leandro CA PD",
    "San Luis Obispo CA PD",
    "San Luis Obispo County (CA) Sheriff",
    "San Mateo CA PD",
    "San Mateo County CA SO",
    "San Pasqual CA PD",
    "San Rafael CA PD",
    "Santa Barbara County CA SO",
    "Santa Clara CA PD",
    "Santa Cruz CA PD (deactivated)",
    "Santa Monica CA PD",
    "Santa Rosa CA PD",
    "Sausalito CA PD",
    "Seal Beach CA PD",
    "Seaside CA PD",
    "Sequoias Community College District CA PD",
    "Simi Valley CA PD",
    "Solano County CA SO",
    "Soledad CA PD",
    "Sonoma County CA SO",
    "South Pasadena CA PD",
    "South San Francisco CA PD",
    "Stallion Springs CA PD",
    "Stanford University CA PD",
    "Stockton CA PD",
    "Suisun City CA PD",
    "Sunnyvale CA PD",
    "Sutter County CA SO",
    "Tiburon CA PD",
    "Tracy CA PD",
    "Truckee CA PD",
    "Tulare County CA SO",
    "Tustin CA PD",
    "Ukiah CA PD",
    "Union City CA PD",
    "Upland CA PD",
    "Vacaville CA PD",
    "Vallejo CA PD",
    "Ventura CA PD",
    "Ventura County CA SO",
    "Ventura County District Attorney's Office CA",
    "Vernon CA PD",
    "Visalia CA PD",
    "Watsonville CA PD",
    "West Covina CA PD",
    "Westminster CA PD",
    "Whittier CA PD",
    "Williams CA PD",
    "Woodland CA PD",
    "Yuba City CA PD",
    "Yuba County Sheriffs Office"
  ],
  "sharing_inbound": [],
  "overview": "Menlo Park CA PD uses Flock Safety technology to capture objective evidence without compromising on individual privacy. Menlo Park CA PD utilizes retroactive search to solve crimes after they've occurred. Additionally, Menlo Park CA PD utilizes real time alerting of hotlist vehicles to capture wanted criminals. In an effort to ensure proper usage and guardrails are in place, they have made the below policies and usage statistics available to the public.",
  "policy_info": "",
  "alpr_policy": "",
  "additional_info": "",
  "download_csv": "",
  "search_audit": "Download CSV",
  "delivery_address": "",
  "sharing_info": "",
  "success_stories": "",
  "disclaimer": "",
  "california_svs": "",
  "sb54": "",
  "last_updated": "",
  "restrictions_on_deployment": "",
  "search_audit_csv": [
    {
      "id": "dfa031f8-e032-4f51-b65e-bed6ea6a2a2e",
      "userId": "***",
      "searchDate": "2026-03-04T16:16:20.014Z",
      "networkCount": "39"
    },
    {
      "id": "05ac6a32-5267-4b2e-bc04-f367200beec6",
      "userId": "***",
      "searchDate": "2026-03-04T22:41:24.991Z",
      "networkCount": "39"
    },
    {
      "id": "69188645-bf66-4ca3-94e7-26e9117d3770",
      "userId": "***",
      "searchDate": "2026-03-04T23:37:10.172Z",
      "networkCount": "1"
    },
    {
      "id": "fb0a7c58-cd31-4c06-9f59-efd38e098b88",
      "userId": "***",
      "searchDate": "2026-03-05T00:19:25.150Z",
      "networkCount": "1"
    },
    {
      "id": "61416bbc-75e8-437e-8a5e-6168fe8e3dbf",
      "userId": "***",
      "searchDate": "2026-03-05T01:10:21.008Z",
      "networkCount": "39"
    },
    {
      "id": "0e95ab70-2290-4119-97ce-4845159e381e",
      "userId": "***",
      "searchDate": "2026-03-05T01:13:36.174Z",
      "networkCount": "39"
    },
    {
      "id": "387eacd6-a067-495b-a485-808197b99efb",
      "userId": "***",
      "searchDate": "2026-03-05T02:38:01.033Z",
      "networkCount": "39"
    },
    {
      "id": "d2ccba22-3a52-44b0-9af5-6be87c4fbc51",
      "userId": "***",
      "searchDate": "2026-03-05T09:51:09.871Z",
      "networkCount": "39"
    },
    {
      "id": "144c0c34-088b-4dc8-adbe-50607ac5dffc",
      "userId": "***",
      "searchDate": "2026-03-05T15:39:33.365Z",
      "networkCount": "39"
    },
    {
      "id": "060c88fe-0155-4ebd-8bb7-691f3e1855d0",
      "userId": "***",
      "searchDate": "2026-03-05T16:22:18.351Z",
      "networkCount": "1"
    },
    {
      "id": "6571fa7a-7fe3-49ed-94f6-64d3adc3308d",
      "userId": "***",
      "searchDate": "2026-03-05T16:33:38.640Z",
      "networkCount": "39"
    },
    {
      "id": "f650c191-ce8b-4d42-91db-e88f44b4da5a",
      "userId": "***",
      "searchDate": "2026-03-05T17:07:57.007Z",
      "networkCount": "39"
    },
    {
      "id": "5b3bf774-d92e-458e-aef3-321110b7f0b7",
      "userId": "***",
      "searchDate": "2026-03-05T20:06:11.258Z",
      "networkCount": "39"
    },
    {
      "id": "00215b1d-c879-471b-86d0-dc2ef924efcd",
      "userId": "***",
      "searchDate": "2026-03-05T20:28:12.826Z",
      "networkCount": "39"
    },
    {
      "id": "1f7a1f5b-126f-4214-bf83-9964d22cbfa3",
      "userId": "***",
      "searchDate": "2026-03-05T20:28:21.909Z",
      "networkCount": "1"
    },
    {
      "id": "6d89fc28-a58b-41ed-9e5f-737a02bbb43e",
      "userId": "***",
      "searchDate": "2026-03-05T23:05:11.422Z",
      "networkCount": "1"
    },
    {
      "id": "035feabf-4dbb-4a0c-ad58-bc7579a855cd",
      "userId": "***",
      "searchDate": "2026-03-06T17:41:15.226Z",
      "networkCount": "39"
    },
    {
      "id": "fc8207ae-a876-4de9-abf8-544af68456d0",
      "userId": "***",
      "searchDate": "2026-03-07T03:07:32.017Z",
      "networkCount": "1"
    },
    {
      "id": "8b616fe6-32bc-4509-a0fa-89d42350b66f",
      "userId": "***",
      "searchDate": "2026-03-07T21:50:32.475Z",
      "networkCount": "39"
    },
    {
      "id": "83342e43-d196-49ec-aa88-0e8833def38d",
      "userId": "***",
      "searchDate": "2026-03-08T11:52:05.658Z",
      "networkCount": "39"
    },
    {
      "id": "485b1381-579a-4eaf-929d-3a483671969c",
      "userId": "***",
      "searchDate": "2026-03-08T12:00:56.755Z",
      "networkCount": "39"
    },
    {
      "id": "f3790ec7-c69f-4a6f-a6dc-7162e2532c44",
      "userId": "***",
      "searchDate": "2026-03-08T12:11:35.358Z",
      "networkCount": "1"
    },
    {
      "id": "a4a66fc8-1475-4c42-a07e-e37754df11fd",
      "userId": "***",
      "searchDate": "2026-03-08T20:55:11.965Z",
      "networkCount": "1"
    },
    {
      "id": "6688f8e6-bf99-48f9-b4e8-0da861004a9b",
      "userId": "***",
      "searchDate": "2026-03-08T21:06:41.934Z",
      "networkCount": "39"
    },
    {
      "id": "b76b16fa-2b64-4d86-8461-776e6d810b53",
      "userId": "***",
      "searchDate": "2026-03-08T21:47:06.503Z",
      "networkCount": "1"
    },
    {
      "id": "90b1381c-d570-4ca9-8efb-05c9915a069d",
      "userId": "***",
      "searchDate": "2026-03-09T16:20:51.617Z",
      "networkCount": "49"
    },
    {
      "id": "d7fa3580-47fc-43f4-9b99-ae09f5b50d54",
      "userId": "***",
      "searchDate": "2026-03-10T03:57:58.665Z",
      "networkCount": "39"
    },
    {
      "id": "fcb596b8-a354-422d-8219-b07197ee3e81",
      "userId": "***",
      "searchDate": "2026-03-10T13:15:20.863Z",
      "networkCount": "39"
    },
    {
      "id": "d6454eb6-6a55-4d57-aa58-43aadc386a13",
      "userId": "***",
      "searchDate": "2026-03-10T13:16:55.235Z",
      "networkCount": "39"
    },
    {
      "id": "bbae8294-c276-4521-9c6c-35aab73ba9a3",
      "userId": "***",
      "searchDate": "2026-03-10T15:41:53.312Z",
      "networkCount": "39"
    },
    {
      "id": "2c493bb1-71c3-4af8-b88a-b07521e20048",
      "userId": "***",
      "searchDate": "2026-03-11T17:23:28.490Z",
      "networkCount": "1"
    },
    {
      "id": "48b818de-cdb3-496e-8614-184a1e7c4cda",
      "userId": "***",
      "searchDate": "2026-03-11T18:24:56.691Z",
      "networkCount": "1"
    },
    {
      "id": "50ce3596-fadc-47b9-aa6f-4ef5977bd859",
      "userId": "***",
      "searchDate": "2026-03-11T19:22:26.587Z",
      "networkCount": "37"
    },
    {
      "id": "9a5a89da-c0be-43e6-8ec4-3cd29958d79e",
      "userId": "***",
      "searchDate": "2026-03-11T20:22:41.525Z",
      "networkCount": "1"
    },
    {
      "id": "55650649-d424-4185-8fb8-07a752084b46",
      "userId": "***",
      "searchDate": "2026-03-11T22:07:38.398Z",
      "networkCount": "39"
    },
    {
      "id": "ae8d5f1b-4dde-488d-9dfd-d8f7ac111f48",
      "userId": "***",
      "searchDate": "2026-03-11T22:11:50.375Z",
      "networkCount": "39"
    },
    {
      "id": "7a2a909a-7eb3-4e62-9c04-74d0175010f1",
      "userId": "***",
      "searchDate": "2026-03-11T23:55:46.764Z",
      "networkCount": "1"
    },
    {
      "id": "c80f090e-fade-4b2d-b569-976dd055891d",
      "userId": "***",
      "searchDate": "2026-03-13T01:15:14.622Z",
      "networkCount": "49"
    },
    {
      "id": "666ce66c-cf25-47d3-9858-445ca4bce468",
      "userId": "***",
      "searchDate": "2026-03-13T02:56:21.335Z",
      "networkCount": "39"
    },
    {
      "id": "13fa76a9-824c-4cf9-a684-e9422e1c1bf5",
      "userId": "***",
      "searchDate": "2026-03-13T03:29:14.611Z",
      "networkCount": "39"
    },
    {
      "id": "a430f0d1-b1e0-44fa-9761-196c92b5db34",
      "userId": "***",
      "searchDate": "2026-03-13T03:52:35.762Z",
      "networkCount": "49"
    },
    {
      "id": "774fbc66-eeaa-4703-8289-5bed35c7d6af",
      "userId": "***",
      "searchDate": "2026-03-13T04:01:24.549Z",
      "networkCount": "49"
    },
    {
      "id": "4ea8ad5d-db50-4242-88c0-c117b47e99a5",
      "userId": "***",
      "searchDate": "2026-03-13T05:11:47.877Z",
      "networkCount": "1"
    },
    {
      "id": "df00d5f4-2c3a-4acd-9c2d-0dc41d339e1a",
      "userId": "***",
      "searchDate": "2026-03-15T01:52:34.204Z",
      "networkCount": "39"
    },
    {
      "id": "f72b8387-a4a5-4935-a5ad-5c7e75c84c9a",
      "userId": "***",
      "searchDate": "2026-03-15T02:27:07.553Z",
      "networkCount": "39"
    },
    {
      "id": "f2d1f673-f742-4211-be85-3afb8f5044ac",
      "userId": "***",
      "searchDate": "2026-03-15T04:42:27.595Z",
      "networkCount": "1"
    },
    {
      "id": "e1e6d741-1321-4f63-8d54-50577f524276",
      "userId": "***",
      "searchDate": "2026-03-15T07:18:15.663Z",
      "networkCount": "39"
    },
    {
      "id": "a8e21d2e-5eb0-40b0-9373-c775d1d4fc39",
      "userId": "***",
      "searchDate": "2026-03-15T07:25:57.058Z",
      "networkCount": "2"
    },
    {
      "id": "c6692cd5-97fe-4823-a228-dbac62f96f76",
      "userId": "***",
      "searchDate": "2026-03-15T07:39:02.106Z",
      "networkCount": "39"
    },
    {
      "id": "9b76c8fc-1b2d-481e-94dd-04fa98de020a",
      "userId": "***",
      "searchDate": "2026-03-16T02:04:20.442Z",
      "networkCount": "1"
    },
    {
      "id": "85b1301f-38b3-4a3c-912e-95225ad405a7",
      "userId": "***",
      "searchDate": "2026-03-16T02:05:16.316Z",
      "networkCount": "39"
    },
    {
      "id": "8f0c3dbd-afc7-4941-a2dd-4db22d067d12",
      "userId": "***",
      "searchDate": "2026-03-16T02:16:28.374Z",
      "networkCount": "39"
    },
    {
      "id": "aaea8f04-158f-4a8a-a7bf-4f63aa874366",
      "userId": "***",
      "searchDate": "2026-03-16T09:30:58.361Z",
      "networkCount": "39"
    },
    {
      "id": "2fa96e6e-090e-441e-adf6-59de3cc86559",
      "userId": "***",
      "searchDate": "2026-03-17T01:43:15.569Z",
      "networkCount": "39"
    },
    {
      "id": "478282b8-cb08-4ec5-88c9-263a1e3164a4",
      "userId": "***",
      "searchDate": "2026-03-17T02:02:22.732Z",
      "networkCount": "39"
    },
    {
      "id": "f317e9fa-bec6-4301-a5a0-e4f6805ec9c4",
      "userId": "***",
      "searchDate": "2026-03-17T03:53:48.925Z",
      "networkCount": "39"
    },
    {
      "id": "6a5241b4-4461-47f7-8d2b-a8b6ab0f09bb",
      "userId": "***",
      "searchDate": "2026-03-17T03:53:56.942Z",
      "networkCount": "37"
    },
    {
      "id": "8f50058d-1684-4611-bbe5-1a45dc1cc23d",
      "userId": "***",
      "searchDate": "2026-03-17T10:52:12.173Z",
      "networkCount": "39"
    },
    {
      "id": "38bfc40a-f866-4862-8795-ab3d41903beb",
      "userId": "***",
      "searchDate": "2026-03-17T10:53:26.504Z",
      "networkCount": "37"
    },
    {
      "id": "d2b02649-d138-40f9-ac1b-78cac5298ff4",
      "userId": "***",
      "searchDate": "2026-03-17T11:00:22.308Z",
      "networkCount": "39"
    },
    {
      "id": "297c8b5d-fc38-4c8a-ba3c-bfc796f7be27",
      "userId": "***",
      "searchDate": "2026-03-17T19:14:59.285Z",
      "networkCount": "49"
    },
    {
      "id": "e8e71a09-b65c-434a-b1b8-ef458758416b",
      "userId": "***",
      "searchDate": "2026-03-17T19:53:51.841Z",
      "networkCount": "49"
    },
    {
      "id": "566a4245-791c-4dfc-ba22-d95c5961ed39",
      "userId": "***",
      "searchDate": "2026-03-17T20:04:28.450Z",
      "networkCount": "49"
    },
    {
      "id": "7acadf90-139a-4e95-a222-5037c71d60a6",
      "userId": "***",
      "searchDate": "2026-03-18T04:30:07.606Z",
      "networkCount": "39"
    },
    {
      "id": "ac7388cb-204d-4850-9ac2-f642c403ee7a",
      "userId": "***",
      "searchDate": "2026-03-18T11:43:20.849Z",
      "networkCount": "39"
    },
    {
      "id": "c8e992a0-b9b3-4dc9-a1a1-c1d1f2c153c7",
      "userId": "***",
      "searchDate": "2026-03-18T15:54:20.810Z",
      "networkCount": "1"
    },
    {
      "id": "e3b4d730-48ee-4ff7-940f-b06f81ab0417",
      "userId": "***",
      "searchDate": "2026-03-18T20:56:58.319Z",
      "networkCount": "49"
    },
    {
      "id": "4300021c-aaa2-44ef-9034-6d3ba9be70ee",
      "userId": "***",
      "searchDate": "2026-03-18T21:07:06.058Z",
      "networkCount": "1"
    },
    {
      "id": "425eb019-5b43-42af-850f-c442b70b435c",
      "userId": "***",
      "searchDate": "2026-03-18T21:07:51.587Z",
      "networkCount": "49"
    },
    {
      "id": "1c742639-f4fe-48f2-88e6-2ed97bc78bd8",
      "userId": "***",
      "searchDate": "2026-03-18T21:54:38.336Z",
      "networkCount": "37"
    },
    {
      "id": "dc7b631d-651f-4f42-9b15-8a84143e99d7",
      "userId": "***",
      "searchDate": "2026-03-18T22:00:13.106Z",
      "networkCount": "49"
    },
    {
      "id": "46339545-b807-4f1f-9b7e-fd19181556dd",
      "userId": "***",
      "searchDate": "2026-03-19T05:17:50.446Z",
      "networkCount": "49"
    },
    {
      "id": "bc0e5764-f426-427d-93d8-5a88f5292957",
      "userId": "***",
      "searchDate": "2026-03-19T05:25:22.202Z",
      "networkCount": "39"
    },
    {
      "id": "77a3f3aa-c95b-47e6-b28a-6a497155d28b",
      "userId": "***",
      "searchDate": "2026-03-19T06:14:33.728Z",
      "networkCount": "39"
    },
    {
      "id": "7796e471-021e-4a9d-97e6-6dd6dcef0376",
      "userId": "***",
      "searchDate": "2026-03-19T07:26:52.955Z",
      "networkCount": "39"
    },
    {
      "id": "2ed798e2-9ce8-4c9e-b241-437f20ee23b6",
      "userId": "***",
      "searchDate": "2026-03-19T14:51:31.287Z",
      "networkCount": "39"
    },
    {
      "id": "78dc6d47-7e5a-4eb9-b66e-2151e16dd991",
      "userId": "***",
      "searchDate": "2026-03-19T17:21:34.342Z",
      "networkCount": "39"
    },
    {
      "id": "5c5dc7f8-9667-42ab-b828-0c9d1af602a2",
      "userId": "***",
      "searchDate": "2026-03-19T19:37:54.300Z",
      "networkCount": "39"
    },
    {
      "id": "ef35d1b0-3571-465e-9286-c61432ce635a",
      "userId": "***",
      "searchDate": "2026-03-19T20:09:18.069Z",
      "networkCount": "1"
    },
    {
      "id": "8f39b438-0678-4cc7-ad83-7d2a0b3eb4e8",
      "userId": "***",
      "searchDate": "2026-03-19T22:03:15.664Z",
      "networkCount": "49"
    },
    {
      "id": "3a93cf18-9ad7-47b9-bec5-6879af36aa06",
      "userId": "***",
      "searchDate": "2026-03-20T01:33:55.674Z",
      "networkCount": "39"
    },
    {
      "id": "86c7b906-5921-454b-afac-c3de0d69cb8a",
      "userId": "***",
      "searchDate": "2026-03-20T01:34:51.296Z",
      "networkCount": "1"
    },
    {
      "id": "fb3bff31-7731-4384-bf4f-72fd25d411d0",
      "userId": "***",
      "searchDate": "2026-03-20T02:06:56.666Z",
      "networkCount": "2"
    },
    {
      "id": "0d893943-1b89-42ed-96d8-ff4b0c4f42cd",
      "userId": "***",
      "searchDate": "2026-03-20T02:46:24.623Z",
      "networkCount": "1"
    },
    {
      "id": "31f32e3d-fa8f-493e-b584-11c9051767e5",
      "userId": "***",
      "searchDate": "2026-03-20T03:46:21.856Z",
      "networkCount": "39"
    },
    {
      "id": "fca6b5e7-b3d8-4a42-b0fb-03c523cf8bb6",
      "userId": "***",
      "searchDate": "2026-03-20T15:15:47.230Z",
      "networkCount": "39"
    },
    {
      "id": "8194c3e0-9e33-4f56-b323-1e02ca87234e",
      "userId": "***",
      "searchDate": "2026-03-20T18:11:16.628Z",
      "networkCount": "39"
    },
    {
      "id": "7ffa0d10-24e9-449d-a82e-937a7a878847",
      "userId": "***",
      "searchDate": "2026-03-20T23:01:05.461Z",
      "networkCount": "1"
    },
    {
      "id": "b47bd5be-1382-415c-88bf-f6598f2184fd",
      "userId": "***",
      "searchDate": "2026-03-21T17:25:13.166Z",
      "networkCount": "39"
    },
    {
      "id": "7397bae2-1318-45d6-90db-52fe3b5f73f5",
      "userId": "***",
      "searchDate": "2026-03-22T10:29:43.332Z",
      "networkCount": "39"
    },
    {
      "id": "13224c2f-027c-45d6-82d9-8c5091b74cbb",
      "userId": "***",
      "searchDate": "2026-03-22T22:21:41.190Z",
      "networkCount": "1"
    },
    {
      "id": "5e9ec2c7-ca16-433f-8750-a55617317be3",
      "userId": "***",
      "searchDate": "2026-03-23T22:08:29.518Z",
      "networkCount": "1"
    },
    {
      "id": "acbc7f39-c97f-48d0-8f88-9a2c9d6f0c86",
      "userId": "***",
      "searchDate": "2026-03-24T03:37:32.735Z",
      "networkCount": "39"
    },
    {
      "id": "59f4a98c-6a2b-4f8e-9e3e-8faa1302d11b",
      "userId": "***",
      "searchDate": "2026-03-24T10:53:32.765Z",
      "networkCount": "39"
    },
    {
      "id": "54973179-1127-40ed-a3ae-3ca010f5fb95",
      "userId": "***",
      "searchDate": "2026-03-24T12:40:27.708Z",
      "networkCount": "39"
    },
    {
      "id": "7591c86e-ecc1-49a8-83c9-f644086369e5",
      "userId": "***",
      "searchDate": "2026-03-24T16:37:28.141Z",
      "networkCount": "2"
    },
    {
      "id": "87df595f-28b9-4010-9139-9fb7442d354b",
      "userId": "***",
      "searchDate": "2026-03-24T17:07:36.837Z",
      "networkCount": "1"
    },
    {
      "id": "16b59387-1fe4-4f14-815b-93309cf6101e",
      "userId": "***",
      "searchDate": "2026-03-24T17:14:03.510Z",
      "networkCount": "1"
    },
    {
      "id": "b4c99b87-cf44-47d3-9170-38abd727aaad",
      "userId": "***",
      "searchDate": "2026-03-25T02:01:30.223Z",
      "networkCount": "39"
    },
    {
      "id": "e7826769-8c36-48ae-a7de-bc81409c2b0a",
      "userId": "***",
      "searchDate": "2026-03-25T02:05:24.911Z",
      "networkCount": "39"
    },
    {
      "id": "fa90a2a5-3cdf-4b8d-a89f-b141d4bf9c4a",
      "userId": "***",
      "searchDate": "2026-03-25T03:00:22.756Z",
      "networkCount": "39"
    },
    {
      "id": "904176ff-36e4-40d2-b7cc-092f2256aee0",
      "userId": "***",
      "searchDate": "2026-03-25T07:45:52.457Z",
      "networkCount": "39"
    },
    {
      "id": "4a868aba-8a63-4e24-9e1a-cf2bff5f9f01",
      "userId": "***",
      "searchDate": "2026-03-25T09:44:43.002Z",
      "networkCount": "39"
    },
    {
      "id": "cb043211-f33b-409b-b00e-22796b8fa8bf",
      "userId": "***",
      "searchDate": "2026-03-25T15:27:36.277Z",
      "networkCount": "49"
    },
    {
      "id": "d14f02fc-ccf1-4bb1-b41f-9ab7eb1f47fa",
      "userId": "***",
      "searchDate": "2026-03-25T15:46:22.505Z",
      "networkCount": "1"
    },
    {
      "id": "0826decd-0a2c-4193-ac43-cd9971ef67fd",
      "userId": "***",
      "searchDate": "2026-03-25T16:28:39.620Z",
      "networkCount": "1"
    },
    {
      "id": "868d012c-3a16-40cb-ab93-9f6a251bd465",
      "userId": "***",
      "searchDate": "2026-03-25T16:48:49.179Z",
      "networkCount": "1"
    },
    {
      "id": "a35c9cc8-28ce-4ba9-b722-8d62b584d490",
      "userId": "***",
      "searchDate": "2026-03-25T16:53:38.581Z",
      "networkCount": "1"
    },
    {
      "id": "353e3898-80cf-4d07-8640-b9727e1f4761",
      "userId": "***",
      "searchDate": "2026-03-25T19:19:01.749Z",
      "networkCount": "39"
    },
    {
      "id": "32ad5e5d-41e0-44e3-9040-343d5d7cd991",
      "userId": "***",
      "searchDate": "2026-03-26T09:05:56.188Z",
      "networkCount": "39"
    },
    {
      "id": "f907bdfe-6fd3-4330-a94b-f500fdecc5cd",
      "userId": "***",
      "searchDate": "2026-03-26T14:47:29.809Z",
      "networkCount": "39"
    },
    {
      "id": "57983c8d-359b-46ef-bffa-79a023294762",
      "userId": "***",
      "searchDate": "2026-03-26T17:36:44.577Z",
      "networkCount": "1"
    },
    {
      "id": "605be047-8b80-4216-b6f4-1a6d4193352a",
      "userId": "***",
      "searchDate": "2026-03-26T17:37:11.056Z",
      "networkCount": "49"
    },
    {
      "id": "64d16aa8-3b48-44fd-a32d-07464c1cbe9b",
      "userId": "***",
      "searchDate": "2026-03-27T19:27:38.788Z",
      "networkCount": "39"
    },
    {
      "id": "5189fb7c-bd64-4a07-9024-36cc8159338f",
      "userId": "***",
      "searchDate": "2026-03-27T20:11:11.952Z",
      "networkCount": "39"
    },
    {
      "id": "dc0df915-d0b0-4cf2-a896-9d18918859f1",
      "userId": "***",
      "searchDate": "2026-03-27T20:47:04.300Z",
      "networkCount": "1"
    },
    {
      "id": "0da47940-1f6d-47c3-a85b-74c648e9bda9",
      "userId": "***",
      "searchDate": "2026-03-30T16:09:05.729Z",
      "networkCount": "39"
    },
    {
      "id": "3a196b26-44e7-4ba0-b3c4-0c6332b85c39",
      "userId": "***",
      "searchDate": "2026-03-30T21:54:38.059Z",
      "networkCount": "49"
    },
    {
      "id": "1c7b2963-1aa0-48dd-8ab0-ff30fb63593a",
      "userId": "***",
      "searchDate": "2026-03-31T10:32:27.301Z",
      "networkCount": "39"
    },
    {
      "id": "193a07b2-c0a1-44dc-91f9-ffdba3e32bc6",
      "userId": "***",
      "searchDate": "2026-03-31T18:04:55.897Z",
      "networkCount": "39"
    },
    {
      "id": "d8b872fe-7fb2-4159-8095-59717e00ec60",
      "userId": "***",
      "searchDate": "2026-03-31T18:32:48.464Z",
      "networkCount": "39"
    },
    {
      "id": "11362337-d6cd-494f-bfb2-75af2e8b21cb",
      "userId": "***",
      "searchDate": "2026-03-31T18:33:51.767Z",
      "networkCount": "39"
    },
    {
      "id": "3ca0e716-4ee8-47ac-a971-2457c04d9b4e",
      "userId": "***",
      "searchDate": "2026-03-31T19:07:15.402Z",
      "networkCount": "39"
    },
    {
      "id": "0d7b3577-67f6-4ec0-b3b0-827e30a2bd53",
      "userId": "***",
      "searchDate": "2026-04-01T09:07:42.639Z",
      "networkCount": "37"
    },
    {
      "id": "f34241f1-d0e8-487e-8447-b792d381efa1",
      "userId": "***",
      "searchDate": "2026-04-01T09:25:15.728Z",
      "networkCount": "37"
    },
    {
      "id": "986dd843-24a8-4194-8023-fd4bacb5f43b",
      "userId": "***",
      "searchDate": "2026-04-01T09:49:28.313Z",
      "networkCount": "39"
    },
    {
      "id": "2b5b22ed-2058-4eb7-953a-e948029f9945",
      "userId": "***",
      "searchDate": "2026-04-01T18:12:56.405Z",
      "networkCount": "1"
    },
    {
      "id": "cadea823-254d-4921-9784-d1504ef4c063",
      "userId": "***",
      "searchDate": "2026-04-01T19:14:56.362Z",
      "networkCount": "381"
    },
    {
      "id": "74f408d4-47b3-4234-8a88-d88e1ec52a64",
      "userId": "***",
      "searchDate": "2026-04-01T20:34:09.587Z",
      "networkCount": "1"
    },
    {
      "id": "e0f3e268-01c8-4e62-b749-2c9b30f95fce",
      "userId": "***",
      "searchDate": "2026-04-01T20:47:58.550Z",
      "networkCount": "39"
    },
    {
      "id": "c846c797-f314-4c08-9657-efc217c68954",
      "userId": "***",
      "searchDate": "2026-04-01T21:00:59.175Z",
      "networkCount": "1"
    },
    {
      "id": "9fb4759c-3ba0-4091-aacb-86ae5fa6da48",
      "userId": "***",
      "searchDate": "2026-04-01T21:04:37.742Z",
      "networkCount": "381"
    },
    {
      "id": "d37ed0e2-90c5-4f6a-bb22-df07fed77f42",
      "userId": "***",
      "searchDate": "2026-04-01T22:55:27.410Z",
      "networkCount": "381"
    },
    {
      "id": "21760737-57d4-4e74-8e14-fdb9c39fd6ba",
      "userId": "***",
      "searchDate": "2026-04-01T23:23:44.245Z",
      "networkCount": "381"
    },
    {
      "id": "495dc93c-4d61-49be-9269-ca6805449593",
      "userId": "***",
      "searchDate": "2026-04-02T15:01:19.742Z",
      "networkCount": "381"
    },
    {
      "id": "b18ab732-6e8a-4f97-bf7f-4d1889df217a",
      "userId": "***",
      "searchDate": "2026-04-02T16:05:43.212Z",
      "networkCount": "357"
    },
    {
      "id": "020f586c-028c-4cee-bacb-0481e51b02a5",
      "userId": "***",
      "searchDate": "2026-04-02T16:22:46.793Z",
      "networkCount": "357"
    },
    {
      "id": "d842c1c8-725d-46a3-9e26-7811a2611a66",
      "userId": "***",
      "searchDate": "2026-04-02T17:20:30.659Z",
      "networkCount": "381"
    },
    {
      "id": "ba81f1ed-d776-41b9-a0a8-8ccb59259532",
      "userId": "***",
      "searchDate": "2026-04-02T18:01:11.012Z",
      "networkCount": "381"
    },
    {
      "id": "e4c8e9f9-adf1-42fb-9c36-ad63a18f0366",
      "userId": "***",
      "searchDate": "2026-04-02T19:20:35.564Z",
      "networkCount": "381"
    },
    {
      "id": "7d2fb885-45a6-4600-aa5c-ded1099eb64f",
      "userId": "***",
      "searchDate": "2026-04-02T20:51:07.890Z",
      "networkCount": "381"
    },
    {
      "id": "db25965a-0f74-4dac-8e62-157de1e60016",
      "userId": "***",
      "searchDate": "2026-04-02T21:10:49.990Z",
      "networkCount": "381"
    }
  ]
}
