{
  "portal": "madera-ca-pd",
  "schema_seen": [
    "id",
    "networkCount",
    "reason",
    "searchDate",
    "userId"
  ],
  "scrape_count": 4,
  "first_scrape": "2026-03-28",
  "last_scrape": "2026-04-19",
  "search_date_min": "2026-02-27",
  "search_date_max": "2026-04-16",
  "row_count": 65,
  "rows": [
    {
      "id": "65917581-32a2-483f-9902-7e66bd86cc83",
      "userId": "***",
      "searchDate": "2026-02-27T21:02:47.433Z",
      "networkCount": "0",
      "reason": "Wanted Person (Arrest Warrant/Fugitive)",
      "first_seen": "2026-03-28"
    },
    {
      "id": "2f88610a-d985-415f-ba11-1195267ad4f7",
      "userId": "***",
      "searchDate": "2026-02-28T11:58:21.614Z",
      "networkCount": "1",
      "reason": "Justice",
      "first_seen": "2026-03-28"
    },
    {
      "id": "bc1d15f4-469f-4638-898e-09340492592d",
      "userId": "***",
      "searchDate": "2026-02-28T12:00:48.006Z",
      "networkCount": "1",
      "reason": "Justice",
      "first_seen": "2026-03-28"
    },
    {
      "id": "0323eb67-40ea-4d0f-9e9a-54c83111e66a",
      "userId": "***",
      "searchDate": "2026-02-28T12:14:04.316Z",
      "networkCount": "1",
      "reason": "Investigation",
      "first_seen": "2026-03-28"
    },
    {
      "id": "361b220d-f998-4060-9429-0929ab2a8edd",
      "userId": "***",
      "searchDate": "2026-02-28T12:44:40.927Z",
      "networkCount": "1",
      "reason": "Suspect ID",
      "first_seen": "2026-03-28"
    },
    {
      "id": "8b524b6e-3bbd-4aa0-9201-8d73067735a3",
      "userId": "***",
      "searchDate": "2026-03-01T16:48:22.382Z",
      "networkCount": "398",
      "reason": "investigation",
      "first_seen": "2026-03-28"
    },
    {
      "id": "af8f3e84-2a9a-4d31-81e2-a7faf4b9caa2",
      "userId": "***",
      "searchDate": "2026-03-01T23:52:11.760Z",
      "networkCount": "398",
      "reason": "investigation",
      "first_seen": "2026-03-28"
    },
    {
      "id": "55cf18f6-d35f-4946-a2fd-0d35ef9e3ce7",
      "userId": "***",
      "searchDate": "2026-03-02T03:55:54.232Z",
      "networkCount": "0",
      "reason": "Driving Under the Influence (DUI/DWI/OWI/OVI)",
      "first_seen": "2026-03-28"
    },
    {
      "id": "d1568a4c-d745-4de1-b27c-6aa8209e82fd",
      "userId": "***",
      "searchDate": "2026-03-03T18:30:51.051Z",
      "networkCount": "368",
      "reason": "Investigation",
      "first_seen": "2026-03-28"
    },
    {
      "id": "6a80cb8c-9253-467a-abb7-0b82e3afaf60",
      "userId": "***",
      "searchDate": "2026-03-04T08:40:06.147Z",
      "networkCount": "1",
      "reason": "Locating trailer",
      "first_seen": "2026-03-28"
    },
    {
      "id": "7cccd44e-3e59-4c8a-b865-b61fd90eea91",
      "userId": "***",
      "searchDate": "2026-03-05T17:54:23.566Z",
      "networkCount": "1",
      "reason": "investigation",
      "first_seen": "2026-03-28"
    },
    {
      "id": "ae0e6d2b-d6af-478e-9d48-4126102456e1",
      "userId": "***",
      "searchDate": "2026-03-05T18:02:22.991Z",
      "networkCount": "1",
      "reason": "investigation",
      "first_seen": "2026-03-28"
    },
    {
      "id": "868af2c3-3b18-474f-87a1-336359925ab9",
      "userId": "***",
      "searchDate": "2026-03-05T18:24:07.914Z",
      "networkCount": "1",
      "reason": "PETTY THEFT FROM CVS WITH THE RO BEING ON FC PROB FOR THEFT AND NUMEROUS PRIOR THEFT CHARGES",
      "first_seen": "2026-03-28"
    },
    {
      "id": "4e338c0d-d52f-4780-91de-80bccc243ba7",
      "userId": "***",
      "searchDate": "2026-03-06T01:00:46.380Z",
      "networkCount": "1",
      "reason": "211",
      "first_seen": "2026-03-28"
    },
    {
      "id": "fc4a35e1-2c23-4d38-9d33-0cc4434dce05",
      "userId": "***",
      "searchDate": "2026-03-06T01:08:02.901Z",
      "networkCount": "1",
      "reason": "ELAW",
      "first_seen": "2026-03-28"
    },
    {
      "id": "367b321b-1fdb-445b-a542-ce54fdefae6b",
      "userId": "***",
      "searchDate": "2026-03-06T02:04:47.187Z",
      "networkCount": "0",
      "reason": "Robbery",
      "first_seen": "2026-03-28"
    },
    {
      "id": "892c44e2-8f9f-46f8-976e-3cdb31297315",
      "userId": "***",
      "searchDate": "2026-03-06T07:26:36.629Z",
      "networkCount": "1",
      "reason": "law enf",
      "first_seen": "2026-03-28"
    },
    {
      "id": "fa1b0103-2aa9-4d81-a6c5-79f03450a584",
      "userId": "***",
      "searchDate": "2026-03-06T10:28:10.527Z",
      "networkCount": "1",
      "reason": "Investigation",
      "first_seen": "2026-03-28"
    },
    {
      "id": "6808de4b-bcec-47a2-993c-419c3b616b14",
      "userId": "***",
      "searchDate": "2026-03-06T17:05:08.679Z",
      "networkCount": "1",
      "reason": "Shooting investigation",
      "first_seen": "2026-03-28"
    },
    {
      "id": "a531b9b5-4288-496a-9bd5-800970fa7451",
      "userId": "***",
      "searchDate": "2026-03-06T19:44:49.175Z",
      "networkCount": "416",
      "reason": "investigation",
      "first_seen": "2026-03-28"
    },
    {
      "id": "9445ad5d-0813-4a81-91d9-afaa3f5888a0",
      "userId": "***",
      "searchDate": "2026-03-07T05:09:20.453Z",
      "networkCount": "1",
      "reason": "Investigation",
      "first_seen": "2026-03-28"
    },
    {
      "id": "17c4956a-f3cd-48ba-9ebf-d96b2558c005",
      "userId": "***",
      "searchDate": "2026-03-10T03:13:52.243Z",
      "networkCount": "1",
      "reason": "traffic collision",
      "first_seen": "2026-03-28"
    },
    {
      "id": "c1a2b1de-3b9f-46be-b00d-4c2adee82a15",
      "userId": "***",
      "searchDate": "2026-03-10T19:12:13.915Z",
      "networkCount": "1",
      "reason": "Investigation",
      "first_seen": "2026-03-28"
    },
    {
      "id": "956e6f54-1a06-48d4-8804-801fde0f7845",
      "userId": "***",
      "searchDate": "2026-03-11T00:06:43.941Z",
      "networkCount": "0",
      "reason": "Alcohol Offenses (Non-DUI)",
      "first_seen": "2026-03-28"
    },
    {
      "id": "99be5ee4-36e5-42a8-ae27-07e19aff30c0",
      "userId": "***",
      "searchDate": "2026-03-11T15:07:01.197Z",
      "networkCount": "398",
      "reason": "ELAW",
      "first_seen": "2026-03-28"
    },
    {
      "id": "9b9bc961-018f-4ba6-97d2-9ccc41a24daf",
      "userId": "***",
      "searchDate": "2026-03-16T05:36:34.027Z",
      "networkCount": "1",
      "reason": "Justice",
      "first_seen": "2026-03-28"
    },
    {
      "id": "471b136f-6fed-413d-90c8-44e5527c84f4",
      "userId": "***",
      "searchDate": "2026-03-17T01:44:23.638Z",
      "networkCount": "0",
      "reason": "Alcohol Offenses (Non-DUI)",
      "first_seen": "2026-03-28"
    },
    {
      "id": "7c79fd9d-b4f2-4360-a9d7-48f10222b4e3",
      "userId": "***",
      "searchDate": "2026-03-17T15:55:15.817Z",
      "networkCount": "889",
      "reason": "Stabbing investigation",
      "first_seen": "2026-03-28"
    },
    {
      "id": "d8d53523-424b-4c76-9561-0be124379a5e",
      "userId": "***",
      "searchDate": "2026-03-17T20:43:50.762Z",
      "networkCount": "398",
      "reason": "Investigation",
      "first_seen": "2026-03-28"
    },
    {
      "id": "17d86f0e-7c3c-470c-bb25-40f719f93ab0",
      "userId": "***",
      "searchDate": "2026-03-17T22:12:17.704Z",
      "networkCount": "1",
      "reason": "Investigation",
      "first_seen": "2026-03-28"
    },
    {
      "id": "686e6ad5-620e-4022-b3dc-09b2d308e78d",
      "userId": "***",
      "searchDate": "2026-03-19T06:51:01.647Z",
      "networkCount": "1",
      "reason": "INVESTIGATION",
      "first_seen": "2026-03-28"
    },
    {
      "id": "698f1c7a-d1fd-4dea-a312-a5bc095e80ca",
      "userId": "***",
      "searchDate": "2026-03-20T18:46:35.197Z",
      "networkCount": "1",
      "reason": "HIT AND RUN SUSP VEH",
      "first_seen": "2026-03-28"
    },
    {
      "id": "4ccfc77f-4d5e-43e4-869a-4ee5f0f90bfb",
      "userId": "***",
      "searchDate": "2026-03-20T19:05:40.274Z",
      "networkCount": "1",
      "reason": "POSSIBLE HIT AND RUN SUSP VEH",
      "first_seen": "2026-03-28"
    },
    {
      "id": "68d1cf0d-f06d-4fb1-8a3e-dd31cf3fe5e4",
      "userId": "***",
      "searchDate": "2026-03-20T20:35:42.710Z",
      "networkCount": "0",
      "reason": "Alcohol Offenses (Non-DUI)",
      "first_seen": "2026-03-28"
    },
    {
      "id": "c0248711-ca9e-4343-83af-cadb3100f6ef",
      "userId": "***",
      "searchDate": "2026-03-20T21:35:57.790Z",
      "networkCount": "0",
      "reason": "Alcohol Offenses (Non-DUI)",
      "first_seen": "2026-03-28"
    },
    {
      "id": "af40ea78-9f6d-4daa-aa64-46f4d7b886a3",
      "userId": "***",
      "searchDate": "2026-03-21T21:37:22.644Z",
      "networkCount": "1",
      "reason": "FOLLOW UP",
      "first_seen": "2026-03-28"
    },
    {
      "id": "518e5530-460c-40ac-8763-94b09d9044b0",
      "userId": "***",
      "searchDate": "2026-03-22T08:26:46.143Z",
      "networkCount": "1",
      "reason": "Justice",
      "first_seen": "2026-03-28"
    },
    {
      "id": "2d0ce8b4-9372-4558-8bcf-423b0211cff7",
      "userId": "***",
      "searchDate": "2026-03-23T07:30:37.356Z",
      "networkCount": "1",
      "reason": "Justice",
      "first_seen": "2026-03-28"
    },
    {
      "id": "61e69253-e762-4da1-8fff-01f855f11c5c",
      "userId": "***",
      "searchDate": "2026-03-23T08:53:45.719Z",
      "networkCount": "1",
      "reason": "Investigation",
      "first_seen": "2026-03-28"
    },
    {
      "id": "90b8d65c-e251-4afb-bdfd-bd8b12704ded",
      "userId": "***",
      "searchDate": "2026-03-23T15:00:47.086Z",
      "networkCount": "1",
      "reason": "Investigation",
      "first_seen": "2026-03-28"
    },
    {
      "id": "2bb8df79-4a2c-42ba-95ea-1e85b43dd08b",
      "userId": "***",
      "searchDate": "2026-03-24T16:19:51.735Z",
      "networkCount": "1",
      "reason": "Investigation",
      "first_seen": "2026-03-28"
    },
    {
      "id": "1ac60df7-6004-41ff-905b-d0a35cc4a248",
      "userId": "***",
      "searchDate": "2026-03-24T22:01:10.517Z",
      "networkCount": "1",
      "reason": "Investigation",
      "first_seen": "2026-03-28"
    },
    {
      "id": "fb412d75-2293-4d32-aebe-76306968e121",
      "userId": "***",
      "searchDate": "2026-03-24T22:09:27.957Z",
      "networkCount": "1",
      "reason": "Investigation",
      "first_seen": "2026-03-28"
    },
    {
      "id": "b0952ec8-fb62-471f-89d3-a4029455d71b",
      "userId": "***",
      "searchDate": "2026-03-24T23:31:37.521Z",
      "networkCount": "1",
      "reason": "Investigation",
      "first_seen": "2026-03-28"
    },
    {
      "id": "2f2de37c-6958-4cdf-8a0f-cbf1d136de8e",
      "userId": "***",
      "searchDate": "2026-03-25T16:43:06.275Z",
      "networkCount": "1",
      "reason": "Investigation",
      "first_seen": "2026-03-28"
    },
    {
      "id": "6ff0ee77-305b-4b37-b134-4838a9fd4ab6",
      "userId": "***",
      "searchDate": "2026-03-25T17:17:20.910Z",
      "networkCount": "1",
      "reason": "Investigation",
      "first_seen": "2026-03-28"
    },
    {
      "id": "42695ef6-9227-490a-b0a6-35692ea29993",
      "userId": "***",
      "searchDate": "2026-03-25T18:10:54.874Z",
      "networkCount": "1",
      "reason": "Investigation",
      "first_seen": "2026-03-28"
    },
    {
      "id": "d3e47b29-5c32-44f7-bd79-81ae07e227f0",
      "userId": "***",
      "searchDate": "2026-03-25T19:00:57.873Z",
      "networkCount": "398",
      "reason": "Investigation",
      "first_seen": "2026-03-28"
    },
    {
      "id": "fd23a5f1-e89c-4c41-9146-b1fe64913bbd",
      "userId": "***",
      "searchDate": "2026-03-25T19:02:41.954Z",
      "networkCount": "1",
      "reason": "investigation",
      "first_seen": "2026-03-28"
    },
    {
      "id": "6bebb468-d5bf-402a-8271-0da830d0a979",
      "userId": "***",
      "searchDate": "2026-03-25T19:34:57.923Z",
      "networkCount": "1",
      "reason": "investigation",
      "first_seen": "2026-03-28"
    },
    {
      "id": "2aaf276d-3c66-4774-8365-1031c5c2a951",
      "userId": "***",
      "searchDate": "2026-03-26T02:13:24.410Z",
      "networkCount": "0",
      "reason": "Alcohol Offenses (Non-DUI)",
      "first_seen": "2026-03-28"
    },
    {
      "id": "022f7659-eb4a-4abd-b7c8-ae09a37f5dc6",
      "userId": "***",
      "searchDate": "2026-03-27T03:15:23.247Z",
      "networkCount": "368",
      "reason": "Investigation",
      "first_seen": "2026-03-28"
    },
    {
      "id": "c7114219-b9b1-4711-b60c-2ad062511c2f",
      "userId": "***",
      "searchDate": "2026-03-29T23:42:10.007Z",
      "networkCount": "1",
      "reason": "Domestic violence/attempted rape/child abuse",
      "first_seen": "2026-04-04"
    },
    {
      "id": "0e758efe-1a1e-4916-804b-c3ea6f064a6b",
      "userId": "***",
      "searchDate": "2026-03-29T23:54:19.553Z",
      "networkCount": "1",
      "reason": "Investigation",
      "first_seen": "2026-04-04"
    },
    {
      "id": "14d5f3eb-39ea-4a1a-847c-63be73ae2c8f",
      "userId": "***",
      "searchDate": "2026-03-30T22:32:52.559Z",
      "networkCount": "398",
      "reason": "Investigation",
      "first_seen": "2026-04-04"
    },
    {
      "id": "78af4846-1cff-44c1-aaa7-93f252a41676",
      "userId": "***",
      "searchDate": "2026-03-31T16:03:19.639Z",
      "networkCount": "1",
      "reason": "Investigation",
      "first_seen": "2026-04-04"
    },
    {
      "id": "46c57252-3cf8-4922-8370-324ecab84fef",
      "userId": "***",
      "searchDate": "2026-04-02T20:40:44.146Z",
      "networkCount": "1",
      "reason": "Investigation",
      "first_seen": "2026-04-04"
    },
    {
      "id": "a7120245-453e-40ca-98a6-90d4ae2af58f",
      "userId": "***",
      "searchDate": "2026-04-03T19:10:55.003Z",
      "networkCount": "1",
      "reason": "Suspect vehicle",
      "first_seen": "2026-04-04"
    },
    {
      "id": "b819daa1-4dee-4106-8939-5aeefdce7cae",
      "userId": "***",
      "searchDate": "2026-04-05T05:01:55.966Z",
      "networkCount": "1",
      "reason": "Justice",
      "first_seen": "2026-04-11"
    },
    {
      "id": "0a2ef44e-e258-4c45-9b84-b8d9e8b80ad9",
      "userId": "***",
      "searchDate": "2026-04-06T15:04:09.954Z",
      "networkCount": "1",
      "reason": "Investigation",
      "first_seen": "2026-04-11"
    },
    {
      "id": "501cbb47-7c4d-44b7-bb27-a2496ec54ccf",
      "userId": "***",
      "searchDate": "2026-04-06T21:20:10.992Z",
      "networkCount": "1",
      "reason": "Investigation",
      "first_seen": "2026-04-11"
    },
    {
      "id": "cdd44242-65f3-4c9f-bf67-0d1274210bce",
      "userId": "***",
      "searchDate": "2026-04-07T02:21:12.637Z",
      "networkCount": "1",
      "reason": "Investigation",
      "first_seen": "2026-04-11"
    },
    {
      "id": "3d8075e1-61d5-46de-ba56-5687a41dcb49",
      "userId": "***",
      "searchDate": "2026-04-11T22:30:30.060Z",
      "networkCount": "1",
      "reason": "Investigation",
      "first_seen": "2026-04-19"
    },
    {
      "id": "00f81200-f0da-4e81-b4a3-c533754a1815",
      "userId": "***",
      "searchDate": "2026-04-12T16:28:47.275Z",
      "networkCount": "1",
      "reason": "investigation",
      "first_seen": "2026-04-19"
    },
    {
      "id": "e0fdff65-47df-42ec-a8b4-cd87b0303be8",
      "userId": "***",
      "searchDate": "2026-04-16T16:20:47.569Z",
      "networkCount": "1",
      "reason": "Investigation",
      "first_seen": "2026-04-19"
    }
  ]
}
